foxypack_instagram_instagrapy-0.0.3.dist-info/METADATA
foxypack_instagram_instagrapy-0.0.3.dist-info/WHEEL
foxypack_instagram_instagrapy-0.0.3.dist-info/entry_points.txt
foxypack_instagram_instagrapy/__init__.py
foxypack_instagram_instagrapy/engine.py
foxypack_instagram_instagrapy-0.0.3.dist-info/RECORD
