Metadata-Version: 2.1
Name: foxypack-instagram-instagrapy
Version: 0.0.3
Summary: Default template for PDM package
Author-Email: shapranov.work@gmail.com
License: MIT
Requires-Python: >=3.10
Requires-Dist: foxypack>=0.0.7
Requires-Dist: instagrapi>=2.1.3
Requires-Dist: pandas>=2.3.3
Requires-Dist: openpyxl>=3.1.5
Provides-Extra: dev
Requires-Dist: ruff>=0.14.0; extra == "dev"
